odm_sfm/__init__.py
odm_sfm/odm_filter.py
odm_sfm/odm_sfm.py
odm_sfm-0.1.0a10.data/scripts/odm_sfm_lla
odm_sfm-0.1.0a10.dist-info/METADATA
odm_sfm-0.1.0a10.dist-info/WHEEL
odm_sfm-0.1.0a10.dist-info/top_level.txt
odm_sfm-0.1.0a10.dist-info/RECORD
