Metadata-Version: 2.1
Name: odm-sfm
Version: 0.1.0a10
Summary: RTK calibrate GPS.
Home-page: https://pypi.org/project/odm-sfm/
Author: Glodon
Author-email: fuh-d@glodon.com
License: None
Platform: Ubuntu
Classifier: Operating System :: POSIX :: Linux
Classifier: Programming Language :: Unix Shell
Classifier: Programming Language :: Python :: 3.6
Requires-Python: >=3.6
Requires-Dist: numpy
Requires-Dist: PyYAML
Requires-Dist: pyproj
Requires-Dist: ExifRead
Requires-Dist: matplotlib
Requires-Dist: opencv-python
Requires-Dist: Pillow
